{"slug":"algoma-wisconsin","city":"Algoma","state":"Wisconsin","years":{"2020":{"population":3035,"violentCrime":2,"violentRate":65.9,"murder":0,"murderRate":0,"rape":0,"robbery":0,"aggravatedAssault":2,"propertyCrime":18,"propertyRate":593.1,"burglary":1,"larceny":17,"motorVehicleTheft":0,"arson":0},"2021":{"population":3026,"violentCrime":2,"violentRate":66.1,"murder":0,"murderRate":0,"rape":0,"robbery":0,"aggravatedAssault":2,"propertyCrime":23,"propertyRate":760.1,"burglary":0,"larceny":22,"motorVehicleTheft":1,"arson":0},"2022":{"population":3205,"violentCrime":5,"violentRate":156,"murder":0,"murderRate":0,"rape":2,"robbery":0,"aggravatedAssault":3,"propertyCrime":15,"propertyRate":468,"burglary":4,"larceny":10,"motorVehicleTheft":1,"arson":1},"2023":{"population":3198,"violentCrime":5,"violentRate":156.3,"murder":0,"murderRate":0,"rape":1,"robbery":0,"aggravatedAssault":4,"propertyCrime":19,"propertyRate":594.1,"burglary":3,"larceny":15,"motorVehicleTheft":1,"arson":0},"2024":{"population":3207,"violentCrime":5,"violentRate":155.9,"murder":0,"murderRate":0,"rape":1,"robbery":0,"aggravatedAssault":4,"propertyCrime":10,"propertyRate":311.8,"burglary":3,"larceny":7,"motorVehicleTheft":0,"arson":0}}}