{"slug":"arcade-georgia","city":"Arcade","state":"Georgia","years":{"2021":{"population":2064,"violentCrime":2,"violentRate":96.9,"murder":1,"murderRate":48.45,"rape":0,"robbery":0,"aggravatedAssault":1,"propertyCrime":44,"propertyRate":2131.8,"burglary":6,"larceny":34,"motorVehicleTheft":4,"arson":0},"2022":{"population":1948,"violentCrime":2,"violentRate":102.7,"murder":0,"murderRate":0,"rape":0,"robbery":0,"aggravatedAssault":2,"propertyCrime":47,"propertyRate":2412.7,"burglary":10,"larceny":34,"motorVehicleTheft":3,"arson":0},"2023":{"population":1952,"violentCrime":7,"violentRate":358.6,"murder":0,"murderRate":0,"rape":0,"robbery":1,"aggravatedAssault":6,"propertyCrime":52,"propertyRate":2663.9,"burglary":6,"larceny":44,"motorVehicleTheft":2,"arson":0},"2024":{"population":2008,"violentCrime":4,"violentRate":199.2,"murder":0,"murderRate":0,"rape":1,"robbery":1,"aggravatedAssault":2,"propertyCrime":28,"propertyRate":1394.4,"burglary":4,"larceny":23,"motorVehicleTheft":1,"arson":0}}}