{"slug":"augusta-maine","city":"Augusta","state":"Maine","years":{"2020":{"population":18653,"violentCrime":75,"violentRate":402.1,"murder":0,"murderRate":0,"rape":21,"robbery":16,"aggravatedAssault":38,"propertyCrime":617,"propertyRate":3307.8,"burglary":75,"larceny":524,"motorVehicleTheft":18,"arson":3},"2021":{"population":18713,"violentCrime":58,"violentRate":309.9,"murder":1,"murderRate":5.34,"rape":18,"robbery":10,"aggravatedAssault":29,"propertyCrime":564,"propertyRate":3013.9,"burglary":61,"larceny":471,"motorVehicleTheft":32,"arson":1},"2022":{"population":19013,"violentCrime":85,"violentRate":447.1,"murder":0,"murderRate":0,"rape":14,"robbery":5,"aggravatedAssault":66,"propertyCrime":737,"propertyRate":3876.3,"burglary":49,"larceny":629,"motorVehicleTheft":59,"arson":1},"2023":{"population":19144,"violentCrime":55,"violentRate":287.3,"murder":2,"murderRate":10.45,"rape":7,"robbery":13,"aggravatedAssault":33,"propertyCrime":809,"propertyRate":4225.9,"burglary":62,"larceny":696,"motorVehicleTheft":51,"arson":1},"2024":{"population":19164,"violentCrime":48,"violentRate":250.5,"murder":1,"murderRate":5.22,"rape":24,"robbery":2,"aggravatedAssault":21,"propertyCrime":784,"propertyRate":4091,"burglary":45,"larceny":703,"motorVehicleTheft":36,"arson":0}}}