{"slug":"bernardsville-new-jersey","city":"Bernardsville","state":"New Jersey","years":{"2020":{"population":7593,"violentCrime":0,"violentRate":0,"murder":0,"murderRate":0,"rape":0,"robbery":0,"aggravatedAssault":0,"propertyCrime":56,"propertyRate":737.5,"burglary":10,"larceny":39,"motorVehicleTheft":7,"arson":0},"2022":{"population":7786,"violentCrime":0,"violentRate":0,"murder":0,"murderRate":0,"rape":0,"robbery":0,"aggravatedAssault":0,"propertyCrime":27,"propertyRate":346.8,"burglary":1,"larceny":20,"motorVehicleTheft":6,"arson":0},"2023":{"population":7900,"violentCrime":1,"violentRate":12.7,"murder":0,"murderRate":0,"rape":1,"robbery":0,"aggravatedAssault":0,"propertyCrime":34,"propertyRate":430.4,"burglary":4,"larceny":25,"motorVehicleTheft":5,"arson":0},"2024":{"population":8018,"violentCrime":3,"violentRate":37.4,"murder":0,"murderRate":0,"rape":0,"robbery":1,"aggravatedAssault":2,"propertyCrime":48,"propertyRate":598.7,"burglary":7,"larceny":39,"motorVehicleTheft":2,"arson":0}}}