{"slug":"bloomfield-connecticut","city":"Bloomfield","state":"Connecticut","years":{"2020":{"population":21294,"violentCrime":35,"violentRate":164.4,"murder":2,"murderRate":9.39,"rape":3,"robbery":17,"aggravatedAssault":13,"propertyCrime":546,"propertyRate":2564.1,"burglary":32,"larceny":451,"motorVehicleTheft":63,"arson":1},"2021":{"population":21254,"violentCrime":41,"violentRate":192.9,"murder":2,"murderRate":9.41,"rape":5,"robbery":11,"aggravatedAssault":23,"propertyCrime":552,"propertyRate":2597.2,"burglary":25,"larceny":474,"motorVehicleTheft":53,"arson":2},"2022":{"population":21461,"violentCrime":18,"violentRate":83.9,"murder":0,"murderRate":0,"rape":1,"robbery":8,"aggravatedAssault":9,"propertyCrime":647,"propertyRate":3014.8,"burglary":34,"larceny":577,"motorVehicleTheft":36,"arson":2},"2023":{"population":21594,"violentCrime":17,"violentRate":78.7,"murder":1,"murderRate":4.63,"rape":9,"robbery":4,"aggravatedAssault":3,"propertyCrime":584,"propertyRate":2704.5,"burglary":23,"larceny":504,"motorVehicleTheft":57,"arson":0},"2024":{"population":22032,"violentCrime":24,"violentRate":108.9,"murder":1,"murderRate":4.54,"rape":4,"robbery":5,"aggravatedAssault":14,"propertyCrime":506,"propertyRate":2296.7,"burglary":63,"larceny":406,"motorVehicleTheft":37,"arson":2}}}