{"slug":"cheviot-ohio","city":"Cheviot","state":"Ohio","years":{"2020":{"population":8195,"violentCrime":15,"violentRate":183,"murder":0,"murderRate":0,"rape":1,"robbery":7,"aggravatedAssault":7,"propertyCrime":228,"propertyRate":2782.2,"burglary":37,"larceny":165,"motorVehicleTheft":26,"arson":0},"2021":{"population":8164,"violentCrime":28,"violentRate":343,"murder":1,"murderRate":12.25,"rape":4,"robbery":7,"aggravatedAssault":16,"propertyCrime":220,"propertyRate":2694.8,"burglary":22,"larceny":163,"motorVehicleTheft":35,"arson":2},"2022":{"population":8579,"violentCrime":18,"violentRate":209.8,"murder":0,"murderRate":0,"rape":4,"robbery":0,"aggravatedAssault":14,"propertyCrime":225,"propertyRate":2622.7,"burglary":41,"larceny":151,"motorVehicleTheft":33,"arson":0},"2023":{"population":8510,"violentCrime":29,"violentRate":340.8,"murder":2,"murderRate":23.5,"rape":1,"robbery":5,"aggravatedAssault":21,"propertyCrime":203,"propertyRate":2385.4,"burglary":13,"larceny":161,"motorVehicleTheft":29,"arson":0},"2024":{"population":8504,"violentCrime":27,"violentRate":317.5,"murder":0,"murderRate":0,"rape":5,"robbery":1,"aggravatedAssault":21,"propertyCrime":176,"propertyRate":2069.6,"burglary":9,"larceny":122,"motorVehicleTheft":45,"arson":0}}}