{"slug":"china-grove-north-carolina","city":"China Grove","state":"North Carolina","years":{"2021":{"population":4256,"violentCrime":3,"violentRate":70.5,"murder":0,"murderRate":0,"rape":0,"robbery":1,"aggravatedAssault":2,"propertyCrime":56,"propertyRate":1315.8,"burglary":16,"larceny":32,"motorVehicleTheft":8,"arson":0},"2022":{"population":4477,"violentCrime":6,"violentRate":134,"murder":1,"murderRate":22.34,"rape":0,"robbery":0,"aggravatedAssault":5,"propertyCrime":71,"propertyRate":1585.9,"burglary":14,"larceny":46,"motorVehicleTheft":11,"arson":1},"2023":{"population":4550,"violentCrime":2,"violentRate":44,"murder":0,"murderRate":0,"rape":1,"robbery":0,"aggravatedAssault":1,"propertyCrime":52,"propertyRate":1142.9,"burglary":7,"larceny":42,"motorVehicleTheft":3,"arson":1},"2024":{"population":4612,"violentCrime":7,"violentRate":151.8,"murder":0,"murderRate":0,"rape":0,"robbery":2,"aggravatedAssault":5,"propertyCrime":51,"propertyRate":1105.8,"burglary":13,"larceny":33,"motorVehicleTheft":5,"arson":0}}}