{"slug":"conroe-texas","city":"Conroe","state":"Texas","years":{"2020":{"population":94451,"violentCrime":175,"violentRate":185.3,"murder":2,"murderRate":2.12,"rape":35,"robbery":47,"aggravatedAssault":91,"propertyCrime":2336,"propertyRate":2473.2,"burglary":246,"larceny":1914,"motorVehicleTheft":176,"arson":2},"2021":{"population":99965,"violentCrime":217,"violentRate":217.1,"murder":5,"murderRate":5,"rape":44,"robbery":31,"aggravatedAssault":137,"propertyCrime":2190,"propertyRate":2190.8,"burglary":286,"larceny":1651,"motorVehicleTheft":253,"arson":4},"2022":{"population":98623,"violentCrime":314,"violentRate":318.4,"murder":3,"murderRate":3.04,"rape":59,"robbery":35,"aggravatedAssault":217,"propertyCrime":2001,"propertyRate":2028.9,"burglary":225,"larceny":1561,"motorVehicleTheft":215,"arson":3},"2023":{"population":106904,"violentCrime":243,"violentRate":227.3,"murder":3,"murderRate":2.81,"rape":43,"robbery":41,"aggravatedAssault":156,"propertyCrime":1712,"propertyRate":1601.4,"burglary":223,"larceny":1311,"motorVehicleTheft":178,"arson":5},"2024":{"population":114592,"violentCrime":279,"violentRate":243.5,"murder":1,"murderRate":0.87,"rape":74,"robbery":41,"aggravatedAssault":163,"propertyCrime":1872,"propertyRate":1633.6,"burglary":161,"larceny":1561,"motorVehicleTheft":150,"arson":2}}}