{"slug":"copperas-cove-texas","city":"Copperas Cove","state":"Texas","years":{"2020":{"population":33333,"violentCrime":144,"violentRate":432,"murder":4,"murderRate":12,"rape":1,"robbery":12,"aggravatedAssault":127,"propertyCrime":712,"propertyRate":2136,"burglary":113,"larceny":553,"motorVehicleTheft":46,"arson":1},"2021":{"population":33613,"violentCrime":126,"violentRate":374.9,"murder":0,"murderRate":0,"rape":29,"robbery":11,"aggravatedAssault":86,"propertyCrime":624,"propertyRate":1856.4,"burglary":114,"larceny":468,"motorVehicleTheft":42,"arson":9},"2022":{"population":37841,"violentCrime":120,"violentRate":317.1,"murder":2,"murderRate":5.29,"rape":35,"robbery":8,"aggravatedAssault":75,"propertyCrime":654,"propertyRate":1728.3,"burglary":89,"larceny":506,"motorVehicleTheft":59,"arson":9},"2023":{"population":38602,"violentCrime":149,"violentRate":386,"murder":1,"murderRate":2.59,"rape":72,"robbery":10,"aggravatedAssault":66,"propertyCrime":665,"propertyRate":1722.7,"burglary":78,"larceny":519,"motorVehicleTheft":68,"arson":3},"2024":{"population":39379,"violentCrime":130,"violentRate":330.1,"murder":1,"murderRate":2.54,"rape":53,"robbery":10,"aggravatedAssault":66,"propertyCrime":529,"propertyRate":1343.4,"burglary":65,"larceny":434,"motorVehicleTheft":30,"arson":0}}}