{"slug":"daphne-alabama","city":"Daphne","state":"Alabama","years":{"2021":{"population":28387,"violentCrime":6,"violentRate":21.1,"murder":0,"murderRate":0,"rape":1,"robbery":1,"aggravatedAssault":4,"propertyCrime":281,"propertyRate":989.9,"burglary":43,"larceny":224,"motorVehicleTheft":14,"arson":0},"2022":{"population":29871,"violentCrime":22,"violentRate":73.7,"murder":1,"murderRate":3.35,"rape":2,"robbery":1,"aggravatedAssault":18,"propertyCrime":365,"propertyRate":1221.9,"burglary":122,"larceny":220,"motorVehicleTheft":23,"arson":0},"2023":{"population":30718,"violentCrime":15,"violentRate":48.8,"murder":5,"murderRate":16.28,"rape":2,"robbery":2,"aggravatedAssault":6,"propertyCrime":353,"propertyRate":1149.2,"burglary":45,"larceny":285,"motorVehicleTheft":23,"arson":0},"2024":{"population":31256,"violentCrime":17,"violentRate":54.4,"murder":0,"murderRate":0,"rape":4,"robbery":2,"aggravatedAssault":11,"propertyCrime":264,"propertyRate":844.6,"burglary":14,"larceny":235,"motorVehicleTheft":15,"arson":0}}}