{"slug":"delaware-ohio","city":"Delaware","state":"Ohio","years":{"2020":{"population":42064,"violentCrime":57,"violentRate":135.5,"murder":0,"murderRate":0,"rape":31,"robbery":4,"aggravatedAssault":22,"propertyCrime":367,"propertyRate":872.5,"burglary":75,"larceny":276,"motorVehicleTheft":16,"arson":11},"2022":{"population":44042,"violentCrime":62,"violentRate":140.8,"murder":0,"murderRate":0,"rape":26,"robbery":1,"aggravatedAssault":35,"propertyCrime":412,"propertyRate":935.5,"burglary":27,"larceny":369,"motorVehicleTheft":16,"arson":5},"2023":{"population":45041,"violentCrime":87,"violentRate":193.2,"murder":3,"murderRate":6.66,"rape":21,"robbery":7,"aggravatedAssault":56,"propertyCrime":365,"propertyRate":810.4,"burglary":26,"larceny":329,"motorVehicleTheft":10,"arson":3},"2024":{"population":46369,"violentCrime":68,"violentRate":146.6,"murder":1,"murderRate":2.16,"rape":13,"robbery":7,"aggravatedAssault":47,"propertyCrime":459,"propertyRate":989.9,"burglary":34,"larceny":399,"motorVehicleTheft":26,"arson":5}}}