{"slug":"devils-lake-north-dakota","city":"Devils Lake","state":"North Dakota","years":{"2020":{"population":7339,"violentCrime":27,"violentRate":367.9,"murder":0,"murderRate":0,"rape":8,"robbery":2,"aggravatedAssault":17,"propertyCrime":269,"propertyRate":3665.3,"burglary":31,"larceny":201,"motorVehicleTheft":37,"arson":2},"2021":{"population":7237,"violentCrime":20,"violentRate":276.4,"murder":0,"murderRate":0,"rape":3,"robbery":1,"aggravatedAssault":16,"propertyCrime":284,"propertyRate":3924.3,"burglary":28,"larceny":211,"motorVehicleTheft":45,"arson":2},"2022":{"population":7212,"violentCrime":35,"violentRate":485.3,"murder":0,"murderRate":0,"rape":15,"robbery":2,"aggravatedAssault":18,"propertyCrime":293,"propertyRate":4062.7,"burglary":37,"larceny":204,"motorVehicleTheft":52,"arson":1}}}