{"slug":"district-heights-maryland","city":"District Heights","state":"Maryland","years":{"2023":{"population":5755,"violentCrime":31,"violentRate":538.7,"murder":3,"murderRate":52.13,"rape":1,"robbery":13,"aggravatedAssault":14,"propertyCrime":140,"propertyRate":2432.7,"burglary":10,"larceny":61,"motorVehicleTheft":69,"arson":2},"2024":{"population":5769,"violentCrime":45,"violentRate":780,"murder":1,"murderRate":17.33,"rape":2,"robbery":7,"aggravatedAssault":35,"propertyCrime":97,"propertyRate":1681.4,"burglary":7,"larceny":50,"motorVehicleTheft":40,"arson":0}}}