{"slug":"el-reno-oklahoma","city":"El Reno","state":"Oklahoma","years":{"2020":{"population":20348,"violentCrime":35,"violentRate":172,"murder":2,"murderRate":9.83,"rape":7,"robbery":4,"aggravatedAssault":22,"propertyCrime":349,"propertyRate":1715.2,"burglary":78,"larceny":220,"motorVehicleTheft":51,"arson":5},"2021":{"population":21018,"violentCrime":49,"violentRate":233.1,"murder":1,"murderRate":4.76,"rape":9,"robbery":5,"aggravatedAssault":34,"propertyCrime":295,"propertyRate":1403.6,"burglary":59,"larceny":193,"motorVehicleTheft":43,"arson":5},"2022":{"population":18385,"violentCrime":32,"violentRate":174.1,"murder":1,"murderRate":5.44,"rape":9,"robbery":1,"aggravatedAssault":21,"propertyCrime":245,"propertyRate":1332.6,"burglary":40,"larceny":173,"motorVehicleTheft":32,"arson":3},"2023":{"population":19318,"violentCrime":47,"violentRate":243.3,"murder":1,"murderRate":5.18,"rape":14,"robbery":3,"aggravatedAssault":29,"propertyCrime":285,"propertyRate":1475.3,"burglary":50,"larceny":202,"motorVehicleTheft":33,"arson":12},"2024":{"population":19965,"violentCrime":41,"violentRate":205.4,"murder":1,"murderRate":5.01,"rape":9,"robbery":2,"aggravatedAssault":29,"propertyCrime":271,"propertyRate":1357.4,"burglary":66,"larceny":184,"motorVehicleTheft":21,"arson":5}}}