{"slug":"gaithersburg-maryland","city":"Gaithersburg","state":"Maryland","years":{"2023":{"population":68682,"violentCrime":159,"violentRate":231.5,"murder":1,"murderRate":1.46,"rape":22,"robbery":44,"aggravatedAssault":92,"propertyCrime":1018,"propertyRate":1482.2,"burglary":123,"larceny":798,"motorVehicleTheft":97,"arson":3},"2024":{"population":69590,"violentCrime":176,"violentRate":252.9,"murder":1,"murderRate":1.44,"rape":20,"robbery":45,"aggravatedAssault":110,"propertyCrime":913,"propertyRate":1312,"burglary":105,"larceny":712,"motorVehicleTheft":96,"arson":0}}}