{"slug":"garden-city-idaho","city":"Garden City","state":"Idaho","years":{"2020":{"population":12084,"violentCrime":84,"violentRate":695.1,"murder":1,"murderRate":8.28,"rape":9,"robbery":2,"aggravatedAssault":72,"propertyCrime":241,"propertyRate":1994.4,"burglary":46,"larceny":176,"motorVehicleTheft":19,"arson":1},"2021":{"population":12018,"violentCrime":94,"violentRate":782.2,"murder":1,"murderRate":8.32,"rape":7,"robbery":2,"aggravatedAssault":84,"propertyCrime":226,"propertyRate":1880.5,"burglary":43,"larceny":154,"motorVehicleTheft":29,"arson":2},"2022":{"population":12279,"violentCrime":86,"violentRate":700.4,"murder":0,"murderRate":0,"rape":14,"robbery":3,"aggravatedAssault":69,"propertyCrime":240,"propertyRate":1954.6,"burglary":57,"larceny":169,"motorVehicleTheft":14,"arson":1},"2023":{"population":13258,"violentCrime":88,"violentRate":663.8,"murder":0,"murderRate":0,"rape":14,"robbery":3,"aggravatedAssault":71,"propertyCrime":215,"propertyRate":1621.7,"burglary":64,"larceny":139,"motorVehicleTheft":12,"arson":2},"2024":{"population":12956,"violentCrime":85,"violentRate":656.1,"murder":0,"murderRate":0,"rape":11,"robbery":1,"aggravatedAssault":73,"propertyCrime":186,"propertyRate":1435.6,"burglary":21,"larceny":148,"motorVehicleTheft":17,"arson":2}}}