{"slug":"groton-village-new-york","city":"Groton Village","state":"New York","years":{"2020":{"population":2211,"violentCrime":0,"violentRate":0,"murder":0,"murderRate":0,"rape":0,"robbery":0,"aggravatedAssault":0,"propertyCrime":35,"propertyRate":1583,"burglary":3,"larceny":30,"motorVehicleTheft":2,"arson":0},"2022":{"population":2183,"violentCrime":0,"violentRate":0,"murder":0,"murderRate":0,"rape":0,"robbery":0,"aggravatedAssault":0,"propertyCrime":14,"propertyRate":641.3,"burglary":2,"larceny":12,"motorVehicleTheft":0,"arson":0},"2024":{"population":2086,"violentCrime":0,"violentRate":0,"murder":0,"murderRate":0,"rape":0,"robbery":0,"aggravatedAssault":0,"propertyCrime":5,"propertyRate":239.7,"burglary":0,"larceny":5,"motorVehicleTheft":0,"arson":0}}}