{"slug":"guymon-oklahoma","city":"Guymon","state":"Oklahoma","years":{"2020":{"population":10939,"violentCrime":24,"violentRate":219.4,"murder":1,"murderRate":9.14,"rape":7,"robbery":3,"aggravatedAssault":13,"propertyCrime":149,"propertyRate":1362.1,"burglary":44,"larceny":84,"motorVehicleTheft":21,"arson":1},"2021":{"population":10960,"violentCrime":32,"violentRate":292,"murder":0,"murderRate":0,"rape":9,"robbery":0,"aggravatedAssault":23,"propertyCrime":163,"propertyRate":1487.2,"burglary":39,"larceny":107,"motorVehicleTheft":17,"arson":4},"2022":{"population":12292,"violentCrime":24,"violentRate":195.2,"murder":0,"murderRate":0,"rape":5,"robbery":3,"aggravatedAssault":16,"propertyCrime":132,"propertyRate":1073.9,"burglary":39,"larceny":82,"motorVehicleTheft":11,"arson":1},"2023":{"population":12124,"violentCrime":21,"violentRate":173.2,"murder":0,"murderRate":0,"rape":7,"robbery":0,"aggravatedAssault":14,"propertyCrime":166,"propertyRate":1369.2,"burglary":40,"larceny":115,"motorVehicleTheft":11,"arson":3},"2024":{"population":12090,"violentCrime":24,"violentRate":198.5,"murder":0,"murderRate":0,"rape":8,"robbery":2,"aggravatedAssault":14,"propertyCrime":123,"propertyRate":1017.4,"burglary":39,"larceny":76,"motorVehicleTheft":8,"arson":0}}}