{"slug":"hellertown-pennsylvania","city":"Hellertown","state":"Pennsylvania","years":{"2023":{"population":6131,"violentCrime":17,"violentRate":277.3,"murder":0,"murderRate":0,"rape":2,"robbery":1,"aggravatedAssault":14,"propertyCrime":62,"propertyRate":1011.3,"burglary":6,"larceny":55,"motorVehicleTheft":1,"arson":0},"2024":{"population":6115,"violentCrime":7,"violentRate":114.5,"murder":0,"murderRate":0,"rape":0,"robbery":0,"aggravatedAssault":7,"propertyCrime":36,"propertyRate":588.7,"burglary":8,"larceny":28,"motorVehicleTheft":0,"arson":0}}}