{"slug":"holbrook-massachusetts","city":"Holbrook","state":"Massachusetts","years":{"2020":{"population":11035,"violentCrime":43,"violentRate":389.7,"murder":0,"murderRate":0,"rape":6,"robbery":3,"aggravatedAssault":34,"propertyCrime":144,"propertyRate":1304.9,"burglary":32,"larceny":99,"motorVehicleTheft":13,"arson":1},"2021":{"population":11163,"violentCrime":44,"violentRate":394.2,"murder":0,"murderRate":0,"rape":8,"robbery":5,"aggravatedAssault":31,"propertyCrime":132,"propertyRate":1182.5,"burglary":18,"larceny":99,"motorVehicleTheft":15,"arson":1},"2022":{"population":11350,"violentCrime":39,"violentRate":343.6,"murder":0,"murderRate":0,"rape":4,"robbery":3,"aggravatedAssault":32,"propertyCrime":134,"propertyRate":1180.6,"burglary":16,"larceny":95,"motorVehicleTheft":23,"arson":1},"2023":{"population":11303,"violentCrime":41,"violentRate":362.7,"murder":0,"murderRate":0,"rape":6,"robbery":1,"aggravatedAssault":34,"propertyCrime":132,"propertyRate":1167.8,"burglary":19,"larceny":102,"motorVehicleTheft":11,"arson":2},"2024":{"population":11462,"violentCrime":36,"violentRate":314.1,"murder":1,"murderRate":8.72,"rape":3,"robbery":4,"aggravatedAssault":28,"propertyCrime":158,"propertyRate":1378.5,"burglary":29,"larceny":113,"motorVehicleTheft":16,"arson":0}}}