{"slug":"homedale-idaho","city":"Homedale","state":"Idaho","years":{"2022":{"population":3095,"violentCrime":15,"violentRate":484.7,"murder":0,"murderRate":0,"rape":1,"robbery":0,"aggravatedAssault":14,"propertyCrime":42,"propertyRate":1357,"burglary":17,"larceny":18,"motorVehicleTheft":7,"arson":0},"2023":{"population":3244,"violentCrime":7,"violentRate":215.8,"murder":0,"murderRate":0,"rape":3,"robbery":0,"aggravatedAssault":4,"propertyCrime":11,"propertyRate":339.1,"burglary":4,"larceny":7,"motorVehicleTheft":0,"arson":0}}}