{"slug":"hugo-oklahoma","city":"Hugo","state":"Oklahoma","years":{"2020":{"population":5067,"violentCrime":31,"violentRate":611.8,"murder":1,"murderRate":19.74,"rape":5,"robbery":4,"aggravatedAssault":21,"propertyCrime":235,"propertyRate":4637.9,"burglary":45,"larceny":164,"motorVehicleTheft":26,"arson":8},"2021":{"population":5047,"violentCrime":46,"violentRate":911.4,"murder":1,"murderRate":19.81,"rape":1,"robbery":1,"aggravatedAssault":43,"propertyCrime":230,"propertyRate":4557.2,"burglary":58,"larceny":147,"motorVehicleTheft":25,"arson":9},"2022":{"population":5215,"violentCrime":25,"violentRate":479.4,"murder":0,"murderRate":0,"rape":1,"robbery":3,"aggravatedAssault":21,"propertyCrime":131,"propertyRate":2512,"burglary":36,"larceny":80,"motorVehicleTheft":15,"arson":2},"2023":{"population":5251,"violentCrime":24,"violentRate":457.1,"murder":1,"murderRate":19.04,"rape":5,"robbery":2,"aggravatedAssault":16,"propertyCrime":127,"propertyRate":2418.6,"burglary":37,"larceny":76,"motorVehicleTheft":14,"arson":4},"2024":{"population":5200,"violentCrime":14,"violentRate":269.2,"murder":0,"murderRate":0,"rape":1,"robbery":0,"aggravatedAssault":13,"propertyCrime":115,"propertyRate":2211.5,"burglary":19,"larceny":77,"motorVehicleTheft":19,"arson":1}}}