{"slug":"irvine-kentucky","city":"Irvine","state":"Kentucky","years":{"2020":{"population":2279,"violentCrime":2,"violentRate":87.8,"murder":0,"murderRate":0,"rape":1,"robbery":0,"aggravatedAssault":1,"propertyCrime":13,"propertyRate":570.4,"burglary":2,"larceny":6,"motorVehicleTheft":5,"arson":0},"2021":{"population":2271,"violentCrime":4,"violentRate":176.1,"murder":0,"murderRate":0,"rape":0,"robbery":0,"aggravatedAssault":4,"propertyCrime":20,"propertyRate":880.7,"burglary":5,"larceny":8,"motorVehicleTheft":7,"arson":0},"2022":{"population":2317,"violentCrime":2,"violentRate":86.3,"murder":0,"murderRate":0,"rape":1,"robbery":1,"aggravatedAssault":0,"propertyCrime":24,"propertyRate":1035.8,"burglary":9,"larceny":13,"motorVehicleTheft":2,"arson":0},"2023":{"population":2289,"violentCrime":1,"violentRate":43.7,"murder":0,"murderRate":0,"rape":0,"robbery":0,"aggravatedAssault":1,"propertyCrime":11,"propertyRate":480.6,"burglary":3,"larceny":6,"motorVehicleTheft":2,"arson":0},"2024":{"population":2261,"violentCrime":4,"violentRate":176.9,"murder":0,"murderRate":0,"rape":0,"robbery":0,"aggravatedAssault":4,"propertyCrime":10,"propertyRate":442.3,"burglary":1,"larceny":6,"motorVehicleTheft":3,"arson":0}}}