{"slug":"irving-texas","city":"Irving","state":"Texas","years":{"2020":{"population":242976,"violentCrime":780,"violentRate":321,"murder":9,"murderRate":3.7,"rape":130,"robbery":222,"aggravatedAssault":419,"propertyCrime":6223,"propertyRate":2561.2,"burglary":673,"larceny":4581,"motorVehicleTheft":969,"arson":11},"2021":{"population":241692,"violentCrime":807,"violentRate":333.9,"murder":12,"murderRate":4.96,"rape":162,"robbery":186,"aggravatedAssault":447,"propertyCrime":5897,"propertyRate":2439.9,"burglary":611,"larceny":4334,"motorVehicleTheft":952,"arson":7},"2022":{"population":254141,"violentCrime":853,"violentRate":335.6,"murder":12,"murderRate":4.72,"rape":144,"robbery":164,"aggravatedAssault":533,"propertyCrime":6433,"propertyRate":2531.3,"burglary":748,"larceny":4698,"motorVehicleTheft":987,"arson":8},"2023":{"population":255203,"violentCrime":772,"violentRate":302.5,"murder":13,"murderRate":5.09,"rape":137,"robbery":180,"aggravatedAssault":442,"propertyCrime":6249,"propertyRate":2448.6,"burglary":621,"larceny":4480,"motorVehicleTheft":1148,"arson":7},"2024":{"population":257460,"violentCrime":709,"violentRate":275.4,"murder":19,"murderRate":7.38,"rape":138,"robbery":147,"aggravatedAssault":405,"propertyCrime":5661,"propertyRate":2198.8,"burglary":644,"larceny":3918,"motorVehicleTheft":1099,"arson":9}}}