{"slug":"jasper-georgia","city":"Jasper","state":"Georgia","years":{"2021":{"population":4074,"violentCrime":9,"violentRate":220.9,"murder":0,"murderRate":0,"rape":1,"robbery":0,"aggravatedAssault":8,"propertyCrime":122,"propertyRate":2994.6,"burglary":17,"larceny":99,"motorVehicleTheft":6,"arson":0},"2022":{"population":4371,"violentCrime":2,"violentRate":45.8,"murder":0,"murderRate":0,"rape":0,"robbery":1,"aggravatedAssault":1,"propertyCrime":72,"propertyRate":1647.2,"burglary":9,"larceny":62,"motorVehicleTheft":1,"arson":0},"2024":{"population":5298,"violentCrime":4,"violentRate":75.5,"murder":0,"murderRate":0,"rape":3,"robbery":0,"aggravatedAssault":1,"propertyCrime":63,"propertyRate":1189.1,"burglary":6,"larceny":55,"motorVehicleTheft":2,"arson":0}}}