{"slug":"knox-indiana","city":"Knox","state":"Indiana","years":{"2021":{"population":3538,"violentCrime":40,"violentRate":1130.6,"murder":0,"murderRate":0,"rape":2,"robbery":1,"aggravatedAssault":37,"propertyCrime":34,"propertyRate":961,"burglary":10,"larceny":16,"motorVehicleTheft":8,"arson":0},"2022":{"population":3583,"violentCrime":12,"violentRate":334.9,"murder":0,"murderRate":0,"rape":0,"robbery":0,"aggravatedAssault":12,"propertyCrime":26,"propertyRate":725.6,"burglary":9,"larceny":14,"motorVehicleTheft":3,"arson":0},"2023":{"population":3606,"violentCrime":12,"violentRate":332.8,"murder":0,"murderRate":0,"rape":1,"robbery":0,"aggravatedAssault":11,"propertyCrime":15,"propertyRate":416,"burglary":4,"larceny":10,"motorVehicleTheft":1,"arson":0},"2024":{"population":3578,"violentCrime":18,"violentRate":503.1,"murder":0,"murderRate":0,"rape":1,"robbery":1,"aggravatedAssault":16,"propertyCrime":19,"propertyRate":531,"burglary":4,"larceny":11,"motorVehicleTheft":4,"arson":0}}}