{"slug":"la-quinta-california","city":"La Quinta","state":"California","years":{"2020":{"population":42228,"violentCrime":46,"violentRate":108.9,"murder":0,"murderRate":0,"rape":1,"robbery":10,"aggravatedAssault":35,"propertyCrime":852,"propertyRate":2017.6,"burglary":119,"larceny":660,"motorVehicleTheft":73,"arson":5},"2022":{"population":38715,"violentCrime":70,"violentRate":180.8,"murder":1,"murderRate":2.58,"rape":4,"robbery":19,"aggravatedAssault":46,"propertyCrime":1004,"propertyRate":2593.3,"burglary":127,"larceny":814,"motorVehicleTheft":63,"arson":0},"2023":{"population":38779,"violentCrime":71,"violentRate":183.1,"murder":1,"murderRate":2.58,"rape":3,"robbery":19,"aggravatedAssault":48,"propertyCrime":944,"propertyRate":2434.3,"burglary":136,"larceny":739,"motorVehicleTheft":69,"arson":0},"2024":{"population":39536,"violentCrime":70,"violentRate":177.1,"murder":1,"murderRate":2.53,"rape":7,"robbery":21,"aggravatedAssault":41,"propertyCrime":769,"propertyRate":1945.1,"burglary":114,"larceny":567,"motorVehicleTheft":88,"arson":3}}}