{"slug":"leslie-michigan","city":"Leslie","state":"Michigan","years":{"2020":{"population":1903,"violentCrime":0,"violentRate":0,"murder":0,"murderRate":0,"rape":0,"robbery":0,"aggravatedAssault":0,"propertyCrime":18,"propertyRate":945.9,"burglary":2,"larceny":15,"motorVehicleTheft":1,"arson":0},"2021":{"population":1886,"violentCrime":4,"violentRate":212.1,"murder":0,"murderRate":0,"rape":2,"robbery":0,"aggravatedAssault":2,"propertyCrime":37,"propertyRate":1961.8,"burglary":5,"larceny":24,"motorVehicleTheft":8,"arson":0},"2022":{"population":1929,"violentCrime":3,"violentRate":155.5,"murder":0,"murderRate":0,"rape":0,"robbery":0,"aggravatedAssault":3,"propertyCrime":18,"propertyRate":933.1,"burglary":3,"larceny":15,"motorVehicleTheft":0,"arson":0},"2023":{"population":1917,"violentCrime":3,"violentRate":156.5,"murder":0,"murderRate":0,"rape":1,"robbery":0,"aggravatedAssault":2,"propertyCrime":14,"propertyRate":730.3,"burglary":3,"larceny":9,"motorVehicleTheft":2,"arson":1},"2024":{"population":1897,"violentCrime":4,"violentRate":210.9,"murder":0,"murderRate":0,"rape":1,"robbery":0,"aggravatedAssault":3,"propertyCrime":8,"propertyRate":421.7,"burglary":3,"larceny":5,"motorVehicleTheft":0,"arson":0}}}