{"slug":"marion-kansas","city":"Marion","state":"Kansas","years":{"2020":{"population":1759,"violentCrime":6,"violentRate":341.1,"murder":0,"murderRate":0,"rape":0,"robbery":0,"aggravatedAssault":6,"propertyCrime":16,"propertyRate":909.6,"burglary":3,"larceny":11,"motorVehicleTheft":2,"arson":0},"2021":{"population":1721,"violentCrime":2,"violentRate":116.2,"murder":0,"murderRate":0,"rape":0,"robbery":0,"aggravatedAssault":2,"propertyCrime":8,"propertyRate":464.8,"burglary":3,"larceny":5,"motorVehicleTheft":0,"arson":0}}}