{"slug":"maxton-north-carolina","city":"Maxton","state":"North Carolina","years":{"2020":{"population":2335,"violentCrime":8,"violentRate":342.6,"murder":0,"murderRate":0,"rape":0,"robbery":8,"aggravatedAssault":0,"propertyCrime":85,"propertyRate":3640.3,"burglary":26,"larceny":52,"motorVehicleTheft":7,"arson":3},"2021":{"population":2321,"violentCrime":13,"violentRate":560.1,"murder":9,"murderRate":387.76,"rape":0,"robbery":3,"aggravatedAssault":1,"propertyCrime":105,"propertyRate":4523.9,"burglary":22,"larceny":71,"motorVehicleTheft":12,"arson":1},"2022":{"population":2110,"violentCrime":18,"violentRate":853.1,"murder":3,"murderRate":142.18,"rape":2,"robbery":1,"aggravatedAssault":12,"propertyCrime":91,"propertyRate":4312.8,"burglary":20,"larceny":59,"motorVehicleTheft":12,"arson":3},"2023":{"population":2103,"violentCrime":9,"violentRate":428,"murder":1,"murderRate":47.55,"rape":0,"robbery":3,"aggravatedAssault":5,"propertyCrime":64,"propertyRate":3043.3,"burglary":23,"larceny":36,"motorVehicleTheft":5,"arson":8},"2024":{"population":2116,"violentCrime":5,"violentRate":236.3,"murder":1,"murderRate":47.26,"rape":0,"robbery":0,"aggravatedAssault":4,"propertyCrime":21,"propertyRate":992.4,"burglary":3,"larceny":15,"motorVehicleTheft":3,"arson":2}}}