{"slug":"maypearl-texas","city":"Maypearl","state":"Texas","years":{"2021":{"population":1060,"violentCrime":0,"violentRate":0,"murder":0,"murderRate":0,"rape":0,"robbery":0,"aggravatedAssault":0,"propertyCrime":3,"propertyRate":283,"burglary":2,"larceny":0,"motorVehicleTheft":1,"arson":0},"2022":{"population":945,"violentCrime":2,"violentRate":211.6,"murder":0,"murderRate":0,"rape":0,"robbery":0,"aggravatedAssault":2,"propertyCrime":3,"propertyRate":317.5,"burglary":1,"larceny":2,"motorVehicleTheft":0,"arson":0},"2023":{"population":953,"violentCrime":0,"violentRate":0,"murder":0,"murderRate":0,"rape":0,"robbery":0,"aggravatedAssault":0,"propertyCrime":0,"propertyRate":0,"burglary":0,"larceny":0,"motorVehicleTheft":0,"arson":0},"2024":{"population":980,"violentCrime":0,"violentRate":0,"murder":0,"murderRate":0,"rape":0,"robbery":0,"aggravatedAssault":0,"propertyCrime":3,"propertyRate":306.1,"burglary":1,"larceny":1,"motorVehicleTheft":1,"arson":0}}}