{"slug":"morton-illinois","city":"Morton","state":"Illinois","years":{"2023":{"population":17452,"violentCrime":33,"violentRate":189.1,"murder":0,"murderRate":0,"rape":6,"robbery":0,"aggravatedAssault":27,"propertyCrime":157,"propertyRate":899.6,"burglary":24,"larceny":115,"motorVehicleTheft":18,"arson":1},"2024":{"population":17592,"violentCrime":15,"violentRate":85.3,"murder":0,"murderRate":0,"rape":5,"robbery":2,"aggravatedAssault":8,"propertyCrime":145,"propertyRate":824.2,"burglary":33,"larceny":103,"motorVehicleTheft":9,"arson":1}}}