{"slug":"nashwauk-minnesota","city":"Nashwauk","state":"Minnesota","years":{"2020":{"population":948,"violentCrime":1,"violentRate":105.5,"murder":0,"murderRate":0,"rape":1,"robbery":0,"aggravatedAssault":0,"propertyCrime":1,"propertyRate":105.5,"burglary":1,"larceny":0,"motorVehicleTheft":0,"arson":0},"2021":{"population":947,"violentCrime":1,"violentRate":105.6,"murder":0,"murderRate":0,"rape":0,"robbery":0,"aggravatedAssault":1,"propertyCrime":1,"propertyRate":105.6,"burglary":0,"larceny":1,"motorVehicleTheft":0,"arson":0},"2022":{"population":962,"violentCrime":0,"violentRate":0,"murder":0,"murderRate":0,"rape":0,"robbery":0,"aggravatedAssault":0,"propertyCrime":1,"propertyRate":104,"burglary":0,"larceny":1,"motorVehicleTheft":0,"arson":0},"2023":{"population":956,"violentCrime":0,"violentRate":0,"murder":0,"murderRate":0,"rape":0,"robbery":0,"aggravatedAssault":0,"propertyCrime":5,"propertyRate":523,"burglary":0,"larceny":5,"motorVehicleTheft":0,"arson":0},"2024":{"population":955,"violentCrime":2,"violentRate":209.4,"murder":0,"murderRate":0,"rape":1,"robbery":0,"aggravatedAssault":1,"propertyCrime":2,"propertyRate":209.4,"burglary":1,"larceny":1,"motorVehicleTheft":0,"arson":0}}}