{"slug":"navarre-ohio","city":"Navarre","state":"Ohio","years":{"2020":{"population":1804,"violentCrime":2,"violentRate":110.9,"murder":0,"murderRate":0,"rape":0,"robbery":0,"aggravatedAssault":2,"propertyCrime":19,"propertyRate":1053.2,"burglary":7,"larceny":10,"motorVehicleTheft":2,"arson":0},"2021":{"population":1788,"violentCrime":2,"violentRate":111.9,"murder":0,"murderRate":0,"rape":0,"robbery":1,"aggravatedAssault":1,"propertyCrime":64,"propertyRate":3579.4,"burglary":58,"larceny":6,"motorVehicleTheft":0,"arson":2},"2024":{"population":1795,"violentCrime":2,"violentRate":111.4,"murder":0,"murderRate":0,"rape":1,"robbery":0,"aggravatedAssault":1,"propertyCrime":11,"propertyRate":612.8,"burglary":3,"larceny":8,"motorVehicleTheft":0,"arson":0}}}