{"slug":"north-tonawanda-new-york","city":"North Tonawanda","state":"New York","years":{"2022":{"population":30358,"violentCrime":48,"violentRate":158.1,"murder":0,"murderRate":0,"rape":9,"robbery":2,"aggravatedAssault":37,"propertyCrime":323,"propertyRate":1064,"burglary":29,"larceny":268,"motorVehicleTheft":26,"arson":5},"2023":{"population":30138,"violentCrime":43,"violentRate":142.7,"murder":0,"murderRate":0,"rape":6,"robbery":7,"aggravatedAssault":30,"propertyCrime":314,"propertyRate":1041.9,"burglary":33,"larceny":264,"motorVehicleTheft":17,"arson":0},"2024":{"population":29898,"violentCrime":46,"violentRate":153.9,"murder":0,"murderRate":0,"rape":6,"robbery":5,"aggravatedAssault":35,"propertyCrime":325,"propertyRate":1087,"burglary":37,"larceny":253,"motorVehicleTheft":35,"arson":2}}}