{"slug":"oakdale-minnesota","city":"Oakdale","state":"Minnesota","years":{"2020":{"population":27990,"violentCrime":32,"violentRate":114.3,"murder":0,"murderRate":0,"rape":10,"robbery":14,"aggravatedAssault":8,"propertyCrime":936,"propertyRate":3344.1,"burglary":76,"larceny":787,"motorVehicleTheft":73,"arson":5},"2021":{"population":27808,"violentCrime":62,"violentRate":223,"murder":0,"murderRate":0,"rape":14,"robbery":15,"aggravatedAssault":33,"propertyCrime":795,"propertyRate":2858.9,"burglary":67,"larceny":648,"motorVehicleTheft":80,"arson":1},"2022":{"population":27681,"violentCrime":43,"violentRate":155.3,"murder":0,"murderRate":0,"rape":9,"robbery":6,"aggravatedAssault":28,"propertyCrime":807,"propertyRate":2915.4,"burglary":40,"larceny":676,"motorVehicleTheft":91,"arson":1},"2023":{"population":27565,"violentCrime":39,"violentRate":141.5,"murder":0,"murderRate":0,"rape":12,"robbery":14,"aggravatedAssault":13,"propertyCrime":471,"propertyRate":1708.7,"burglary":29,"larceny":416,"motorVehicleTheft":26,"arson":2},"2024":{"population":28214,"violentCrime":51,"violentRate":180.8,"murder":0,"murderRate":0,"rape":6,"robbery":13,"aggravatedAssault":32,"propertyCrime":497,"propertyRate":1761.5,"burglary":43,"larceny":425,"motorVehicleTheft":29,"arson":0}}}