{"slug":"osceola-iowa","city":"Osceola","state":"Iowa","years":{"2020":{"population":5275,"violentCrime":16,"violentRate":303.3,"murder":0,"murderRate":0,"rape":2,"robbery":0,"aggravatedAssault":14,"propertyCrime":104,"propertyRate":1971.6,"burglary":13,"larceny":85,"motorVehicleTheft":6,"arson":5},"2021":{"population":5320,"violentCrime":15,"violentRate":282,"murder":0,"murderRate":0,"rape":2,"robbery":1,"aggravatedAssault":12,"propertyCrime":92,"propertyRate":1729.3,"burglary":20,"larceny":66,"motorVehicleTheft":6,"arson":4},"2022":{"population":5654,"violentCrime":25,"violentRate":442.2,"murder":0,"murderRate":0,"rape":4,"robbery":1,"aggravatedAssault":20,"propertyCrime":79,"propertyRate":1397.2,"burglary":16,"larceny":56,"motorVehicleTheft":7,"arson":1},"2023":{"population":5644,"violentCrime":12,"violentRate":212.6,"murder":0,"murderRate":0,"rape":5,"robbery":0,"aggravatedAssault":7,"propertyCrime":95,"propertyRate":1683.2,"burglary":17,"larceny":70,"motorVehicleTheft":8,"arson":0},"2024":{"population":5617,"violentCrime":9,"violentRate":160.2,"murder":1,"murderRate":17.8,"rape":0,"robbery":0,"aggravatedAssault":8,"propertyCrime":115,"propertyRate":2047.4,"burglary":17,"larceny":94,"motorVehicleTheft":4,"arson":2}}}