{"slug":"palos-hills-illinois","city":"Palos Hills","state":"Illinois","years":{"2020":{"population":17013,"violentCrime":13,"violentRate":76.4,"murder":0,"murderRate":0,"rape":0,"robbery":6,"aggravatedAssault":7,"propertyCrime":0,"propertyRate":0,"burglary":8,"larceny":0,"motorVehicleTheft":2,"arson":1},"2022":{"population":17790,"violentCrime":12,"violentRate":67.5,"murder":0,"murderRate":0,"rape":1,"robbery":1,"aggravatedAssault":10,"propertyCrime":82,"propertyRate":460.9,"burglary":17,"larceny":54,"motorVehicleTheft":11,"arson":0},"2023":{"population":17600,"violentCrime":12,"violentRate":68.2,"murder":0,"murderRate":0,"rape":5,"robbery":1,"aggravatedAssault":6,"propertyCrime":121,"propertyRate":687.5,"burglary":20,"larceny":78,"motorVehicleTheft":23,"arson":1},"2024":{"population":17532,"violentCrime":12,"violentRate":68.4,"murder":0,"murderRate":0,"rape":0,"robbery":3,"aggravatedAssault":9,"propertyCrime":72,"propertyRate":410.7,"burglary":22,"larceny":35,"motorVehicleTheft":15,"arson":2}}}