{"slug":"rantoul-illinois","city":"Rantoul","state":"Illinois","years":{"2021":{"population":12241,"violentCrime":48,"violentRate":392.1,"murder":0,"murderRate":0,"rape":12,"robbery":6,"aggravatedAssault":30,"propertyCrime":217,"propertyRate":1772.7,"burglary":43,"larceny":162,"motorVehicleTheft":12,"arson":2},"2022":{"population":11971,"violentCrime":73,"violentRate":609.8,"murder":5,"murderRate":41.77,"rape":18,"robbery":3,"aggravatedAssault":47,"propertyCrime":266,"propertyRate":2222,"burglary":57,"larceny":207,"motorVehicleTheft":2,"arson":4},"2023":{"population":12024,"violentCrime":72,"violentRate":598.8,"murder":1,"murderRate":8.32,"rape":14,"robbery":7,"aggravatedAssault":50,"propertyCrime":220,"propertyRate":1829.7,"burglary":63,"larceny":134,"motorVehicleTheft":23,"arson":2},"2024":{"population":11835,"violentCrime":65,"violentRate":549.2,"murder":1,"murderRate":8.45,"rape":8,"robbery":9,"aggravatedAssault":47,"propertyCrime":210,"propertyRate":1774.4,"burglary":67,"larceny":127,"motorVehicleTheft":16,"arson":13}}}