{"slug":"richland-township-saginaw-county-michigan","city":"Richland Township, Saginaw County","state":"Michigan","years":{"2020":{"population":3904,"violentCrime":5,"violentRate":128.1,"murder":0,"murderRate":0,"rape":0,"robbery":0,"aggravatedAssault":5,"propertyCrime":22,"propertyRate":563.5,"burglary":3,"larceny":17,"motorVehicleTheft":2,"arson":0},"2021":{"population":3891,"violentCrime":11,"violentRate":282.7,"murder":0,"murderRate":0,"rape":1,"robbery":0,"aggravatedAssault":10,"propertyCrime":9,"propertyRate":231.3,"burglary":3,"larceny":6,"motorVehicleTheft":0,"arson":0},"2022":{"population":3916,"violentCrime":5,"violentRate":127.7,"murder":0,"murderRate":0,"rape":0,"robbery":0,"aggravatedAssault":5,"propertyCrime":10,"propertyRate":255.4,"burglary":3,"larceny":7,"motorVehicleTheft":0,"arson":0},"2023":{"population":3894,"violentCrime":7,"violentRate":179.8,"murder":0,"murderRate":0,"rape":0,"robbery":0,"aggravatedAssault":7,"propertyCrime":8,"propertyRate":205.4,"burglary":3,"larceny":3,"motorVehicleTheft":2,"arson":0},"2024":{"population":3871,"violentCrime":2,"violentRate":51.7,"murder":0,"murderRate":0,"rape":0,"robbery":0,"aggravatedAssault":2,"propertyCrime":14,"propertyRate":361.7,"burglary":1,"larceny":9,"motorVehicleTheft":4,"arson":0}}}