{"slug":"roma-texas","city":"Roma","state":"Texas","years":{"2020":{"population":11559,"violentCrime":30,"violentRate":259.5,"murder":1,"murderRate":8.65,"rape":2,"robbery":1,"aggravatedAssault":26,"propertyCrime":103,"propertyRate":891.1,"burglary":15,"larceny":71,"motorVehicleTheft":17,"arson":1},"2021":{"population":11534,"violentCrime":33,"violentRate":286.1,"murder":0,"murderRate":0,"rape":6,"robbery":1,"aggravatedAssault":26,"propertyCrime":97,"propertyRate":841,"burglary":18,"larceny":67,"motorVehicleTheft":12,"arson":1},"2022":{"population":11547,"violentCrime":39,"violentRate":337.8,"murder":0,"murderRate":0,"rape":2,"robbery":2,"aggravatedAssault":35,"propertyCrime":85,"propertyRate":736.1,"burglary":11,"larceny":65,"motorVehicleTheft":9,"arson":0},"2023":{"population":11503,"violentCrime":26,"violentRate":226,"murder":0,"murderRate":0,"rape":3,"robbery":1,"aggravatedAssault":22,"propertyCrime":100,"propertyRate":869.3,"burglary":16,"larceny":81,"motorVehicleTheft":3,"arson":1},"2024":{"population":11552,"violentCrime":30,"violentRate":259.7,"murder":0,"murderRate":0,"rape":2,"robbery":2,"aggravatedAssault":26,"propertyCrime":79,"propertyRate":683.9,"burglary":8,"larceny":58,"motorVehicleTheft":13,"arson":0}}}