{"slug":"roseville-michigan","city":"Roseville","state":"Michigan","years":{"2020":{"population":46983,"violentCrime":217,"violentRate":461.9,"murder":5,"murderRate":10.64,"rape":49,"robbery":30,"aggravatedAssault":133,"propertyCrime":1138,"propertyRate":2422.2,"burglary":110,"larceny":902,"motorVehicleTheft":126,"arson":7},"2021":{"population":46456,"violentCrime":255,"violentRate":548.9,"murder":1,"murderRate":2.15,"rape":39,"robbery":34,"aggravatedAssault":181,"propertyCrime":1193,"propertyRate":2568,"burglary":113,"larceny":924,"motorVehicleTheft":156,"arson":5},"2022":{"population":46719,"violentCrime":249,"violentRate":533,"murder":4,"murderRate":8.56,"rape":27,"robbery":24,"aggravatedAssault":194,"propertyCrime":1700,"propertyRate":3638.8,"burglary":119,"larceny":1360,"motorVehicleTheft":221,"arson":6},"2023":{"population":46425,"violentCrime":240,"violentRate":517,"murder":4,"murderRate":8.62,"rape":31,"robbery":26,"aggravatedAssault":179,"propertyCrime":1680,"propertyRate":3618.7,"burglary":133,"larceny":1262,"motorVehicleTheft":285,"arson":9},"2024":{"population":46358,"violentCrime":242,"violentRate":522,"murder":1,"murderRate":2.16,"rape":33,"robbery":18,"aggravatedAssault":190,"propertyCrime":1535,"propertyRate":3311.2,"burglary":135,"larceny":1198,"motorVehicleTheft":202,"arson":9}}}