{"slug":"schaumburg-illinois","city":"Schaumburg","state":"Illinois","years":{"2020":{"population":72733,"violentCrime":78,"violentRate":107.2,"murder":0,"murderRate":0,"rape":28,"robbery":24,"aggravatedAssault":26,"propertyCrime":0,"propertyRate":0,"burglary":72,"larceny":0,"motorVehicleTheft":65,"arson":0},"2022":{"population":75745,"violentCrime":69,"violentRate":91.1,"murder":0,"murderRate":0,"rape":22,"robbery":17,"aggravatedAssault":30,"propertyCrime":1613,"propertyRate":2129.5,"burglary":77,"larceny":1441,"motorVehicleTheft":95,"arson":3},"2023":{"population":75140,"violentCrime":68,"violentRate":90.5,"murder":2,"murderRate":2.66,"rape":17,"robbery":17,"aggravatedAssault":32,"propertyCrime":1533,"propertyRate":2040.2,"burglary":109,"larceny":1325,"motorVehicleTheft":99,"arson":3},"2024":{"population":74882,"violentCrime":68,"violentRate":90.8,"murder":0,"murderRate":0,"rape":21,"robbery":17,"aggravatedAssault":30,"propertyCrime":1796,"propertyRate":2398.4,"burglary":130,"larceny":1578,"motorVehicleTheft":88,"arson":1}}}