{"slug":"south-holland-illinois","city":"South Holland","state":"Illinois","years":{"2020":{"population":21218,"violentCrime":59,"violentRate":278.1,"murder":0,"murderRate":0,"rape":10,"robbery":31,"aggravatedAssault":18,"propertyCrime":0,"propertyRate":0,"burglary":44,"larceny":0,"motorVehicleTheft":127,"arson":2},"2022":{"population":20626,"violentCrime":83,"violentRate":402.4,"murder":4,"murderRate":19.39,"rape":21,"robbery":25,"aggravatedAssault":33,"propertyCrime":416,"propertyRate":2016.9,"burglary":31,"larceny":262,"motorVehicleTheft":123,"arson":2},"2023":{"population":20342,"violentCrime":92,"violentRate":452.3,"murder":3,"murderRate":14.75,"rape":19,"robbery":33,"aggravatedAssault":37,"propertyCrime":471,"propertyRate":2315.4,"burglary":85,"larceny":194,"motorVehicleTheft":192,"arson":1},"2024":{"population":20192,"violentCrime":68,"violentRate":336.8,"murder":2,"murderRate":9.9,"rape":8,"robbery":22,"aggravatedAssault":36,"propertyCrime":427,"propertyRate":2114.7,"burglary":61,"larceny":249,"motorVehicleTheft":117,"arson":2}}}