{"slug":"south-salt-lake-utah","city":"South Salt Lake","state":"Utah","years":{"2020":{"population":25816,"violentCrime":249,"violentRate":964.5,"murder":4,"murderRate":15.49,"rape":39,"robbery":73,"aggravatedAssault":133,"propertyCrime":2376,"propertyRate":9203.6,"burglary":235,"larceny":1679,"motorVehicleTheft":462,"arson":12},"2021":{"population":25422,"violentCrime":261,"violentRate":1026.7,"murder":3,"murderRate":11.8,"rape":44,"robbery":54,"aggravatedAssault":160,"propertyCrime":1936,"propertyRate":7615.5,"burglary":146,"larceny":1359,"motorVehicleTheft":431,"arson":3},"2024":{"population":25930,"violentCrime":199,"violentRate":767.5,"murder":2,"murderRate":7.71,"rape":41,"robbery":39,"aggravatedAssault":117,"propertyCrime":1523,"propertyRate":5873.5,"burglary":161,"larceny":1210,"motorVehicleTheft":152,"arson":1}}}