{"slug":"south-toms-river-new-jersey","city":"South Toms River","state":"New Jersey","years":{"2020":{"population":3701,"violentCrime":7,"violentRate":189.1,"murder":0,"murderRate":0,"rape":0,"robbery":0,"aggravatedAssault":7,"propertyCrime":25,"propertyRate":675.5,"burglary":5,"larceny":18,"motorVehicleTheft":2,"arson":0},"2023":{"population":3787,"violentCrime":3,"violentRate":79.2,"murder":0,"murderRate":0,"rape":0,"robbery":1,"aggravatedAssault":2,"propertyCrime":70,"propertyRate":1848.4,"burglary":18,"larceny":51,"motorVehicleTheft":1,"arson":0},"2024":{"population":3858,"violentCrime":5,"violentRate":129.6,"murder":0,"murderRate":0,"rape":0,"robbery":0,"aggravatedAssault":5,"propertyCrime":32,"propertyRate":829.4,"burglary":10,"larceny":22,"motorVehicleTheft":0,"arson":0}}}