{"slug":"spring-valley-village-new-york","city":"Spring Valley Village","state":"New York","years":{"2020":{"population":32356,"violentCrime":96,"violentRate":296.7,"murder":2,"murderRate":6.18,"rape":11,"robbery":24,"aggravatedAssault":59,"propertyCrime":343,"propertyRate":1060.1,"burglary":41,"larceny":289,"motorVehicleTheft":13,"arson":1},"2021":{"population":32340,"violentCrime":93,"violentRate":287.6,"murder":3,"murderRate":9.28,"rape":7,"robbery":13,"aggravatedAssault":70,"propertyCrime":255,"propertyRate":788.5,"burglary":23,"larceny":221,"motorVehicleTheft":11,"arson":3},"2022":{"population":33044,"violentCrime":111,"violentRate":335.9,"murder":2,"murderRate":6.05,"rape":9,"robbery":37,"aggravatedAssault":63,"propertyCrime":545,"propertyRate":1649.3,"burglary":33,"larceny":503,"motorVehicleTheft":9,"arson":5},"2023":{"population":32846,"violentCrime":118,"violentRate":359.3,"murder":1,"murderRate":3.04,"rape":4,"robbery":35,"aggravatedAssault":78,"propertyCrime":632,"propertyRate":1924.1,"burglary":20,"larceny":608,"motorVehicleTheft":4,"arson":0},"2024":{"population":32973,"violentCrime":119,"violentRate":360.9,"murder":1,"murderRate":3.03,"rape":14,"robbery":36,"aggravatedAssault":68,"propertyCrime":716,"propertyRate":2171.5,"burglary":126,"larceny":578,"motorVehicleTheft":12,"arson":1}}}