{"slug":"ward-arkansas","city":"Ward","state":"Arkansas","years":{"2020":{"population":5517,"violentCrime":66,"violentRate":1196.3,"murder":1,"murderRate":18.13,"rape":8,"robbery":4,"aggravatedAssault":53,"propertyCrime":109,"propertyRate":1975.7,"burglary":32,"larceny":66,"motorVehicleTheft":11,"arson":3},"2021":{"population":5649,"violentCrime":48,"violentRate":849.7,"murder":1,"murderRate":17.7,"rape":7,"robbery":1,"aggravatedAssault":39,"propertyCrime":89,"propertyRate":1575.5,"burglary":22,"larceny":57,"motorVehicleTheft":10,"arson":1},"2022":{"population":6621,"violentCrime":46,"violentRate":694.8,"murder":0,"murderRate":0,"rape":3,"robbery":2,"aggravatedAssault":41,"propertyCrime":129,"propertyRate":1948.3,"burglary":35,"larceny":87,"motorVehicleTheft":7,"arson":1},"2023":{"population":6908,"violentCrime":46,"violentRate":665.9,"murder":0,"murderRate":0,"rape":9,"robbery":1,"aggravatedAssault":36,"propertyCrime":92,"propertyRate":1331.8,"burglary":20,"larceny":60,"motorVehicleTheft":12,"arson":1},"2024":{"population":7108,"violentCrime":20,"violentRate":281.4,"murder":0,"murderRate":0,"rape":4,"robbery":2,"aggravatedAssault":14,"propertyCrime":76,"propertyRate":1069.2,"burglary":14,"larceny":55,"motorVehicleTheft":7,"arson":0}}}