{"slug":"wautoma-wisconsin","city":"Wautoma","state":"Wisconsin","years":{"2020":{"population":2135,"violentCrime":2,"violentRate":93.7,"murder":0,"murderRate":0,"rape":1,"robbery":0,"aggravatedAssault":1,"propertyCrime":244,"propertyRate":11428.6,"burglary":3,"larceny":239,"motorVehicleTheft":2,"arson":0},"2022":{"population":2252,"violentCrime":2,"violentRate":88.8,"murder":0,"murderRate":0,"rape":0,"robbery":0,"aggravatedAssault":2,"propertyCrime":21,"propertyRate":932.5,"burglary":1,"larceny":18,"motorVehicleTheft":2,"arson":0},"2023":{"population":2242,"violentCrime":0,"violentRate":0,"murder":0,"murderRate":0,"rape":0,"robbery":0,"aggravatedAssault":0,"propertyCrime":15,"propertyRate":669,"burglary":0,"larceny":15,"motorVehicleTheft":0,"arson":0},"2024":{"population":2223,"violentCrime":0,"violentRate":0,"murder":0,"murderRate":0,"rape":0,"robbery":0,"aggravatedAssault":0,"propertyCrime":40,"propertyRate":1799.4,"burglary":2,"larceny":35,"motorVehicleTheft":3,"arson":0}}}