{"slug":"weston-missouri","city":"Weston","state":"Missouri","years":{"2021":{"population":1854,"violentCrime":3,"violentRate":161.8,"murder":1,"murderRate":53.94,"rape":1,"robbery":1,"aggravatedAssault":0,"propertyCrime":35,"propertyRate":1887.8,"burglary":6,"larceny":28,"motorVehicleTheft":1,"arson":1},"2022":{"population":1772,"violentCrime":4,"violentRate":225.7,"murder":0,"murderRate":0,"rape":1,"robbery":1,"aggravatedAssault":2,"propertyCrime":18,"propertyRate":1015.8,"burglary":1,"larceny":16,"motorVehicleTheft":1,"arson":0},"2023":{"population":1801,"violentCrime":0,"violentRate":0,"murder":0,"murderRate":0,"rape":0,"robbery":0,"aggravatedAssault":0,"propertyCrime":11,"propertyRate":610.8,"burglary":2,"larceny":9,"motorVehicleTheft":0,"arson":0},"2024":{"population":1829,"violentCrime":0,"violentRate":0,"murder":0,"murderRate":0,"rape":0,"robbery":0,"aggravatedAssault":0,"propertyCrime":22,"propertyRate":1202.8,"burglary":3,"larceny":16,"motorVehicleTheft":3,"arson":0}}}