{"slug":"woodland-park-new-jersey","city":"Woodland Park","state":"New Jersey","years":{"2020":{"population":12653,"violentCrime":12,"violentRate":94.8,"murder":0,"murderRate":0,"rape":0,"robbery":1,"aggravatedAssault":11,"propertyCrime":122,"propertyRate":964.2,"burglary":11,"larceny":99,"motorVehicleTheft":12,"arson":0},"2021":{"population":13278,"violentCrime":7,"violentRate":52.7,"murder":0,"murderRate":0,"rape":0,"robbery":1,"aggravatedAssault":6,"propertyCrime":137,"propertyRate":1031.8,"burglary":5,"larceny":113,"motorVehicleTheft":19,"arson":0},"2022":{"population":13171,"violentCrime":7,"violentRate":53.1,"murder":0,"murderRate":0,"rape":0,"robbery":1,"aggravatedAssault":6,"propertyCrime":143,"propertyRate":1085.7,"burglary":8,"larceny":127,"motorVehicleTheft":8,"arson":0},"2023":{"population":13123,"violentCrime":9,"violentRate":68.6,"murder":0,"murderRate":0,"rape":2,"robbery":0,"aggravatedAssault":7,"propertyCrime":174,"propertyRate":1325.9,"burglary":13,"larceny":142,"motorVehicleTheft":19,"arson":1},"2024":{"population":13331,"violentCrime":10,"violentRate":75,"murder":0,"murderRate":0,"rape":3,"robbery":0,"aggravatedAssault":7,"propertyCrime":132,"propertyRate":990.2,"burglary":19,"larceny":101,"motorVehicleTheft":12,"arson":0}}}